vyos_modular/main.py
vyos_modular/common/commands.py
vyos_modular/common/config.py
vyos_modular/core_build/builder.py
vyos_modular/iso_build/builder.py
vyos_modular/iso_customize/builder.py
vyos_modular/templates/playbook.yml.j2
vyos_modular/templates/sample_config.yml
vyos_modular-2.4.0.dist-info/METADATA
vyos_modular-2.4.0.dist-info/WHEEL
vyos_modular-2.4.0.dist-info/entry_points.txt
vyos_modular-2.4.0.dist-info/top_level.txt
vyos_modular-2.4.0.dist-info/RECORD
