Metadata-Version: 2.1
Name: vyos_modular
Version: 2.4.0
Summary: A modular customization system for vyos ISOs
Requires-Dist: pyyaml ==6.0
Requires-Dist: Jinja2 ==3.1.2
